{"E+dfkwZX5I54T9pOgh2cVQ==":"dsc-7-1820x1205.jpg","A/HDNM5cFRJ6wuqWm0JHXQ==":"kujicam-2019-05-04-00-48-11-developed.jpg","JkWFIKIXrV259stZ4t4Qfw==":"kujicam-2019-05-04-00-48-11-developed-1.jpg","RPt2tNDpdEED2qqKOQ/ROQ==":"mbr.jpg","Pk6j3OLyStz0VA8naq3eoQ==":"mbr-1.jpg","whKOmW73H2eSjb18VpHQyA==":"mbr-2.jpg","dXXemKqKCPLj3BxH7f3uxg==":"mbr-3.jpg","7OsKQPvziK/xHCshdY2OXg==":"mbr-4.jpg","hhx7RcBmeYQC2QN9TJlJaQ==":"mbr-5.jpg","pQo3B8oQ2/4EppOB2BtRww==":"mbr-6.jpg","LbSVkjM79TIScwI/U+HbkQ==":"mbr-7.jpg","qrdTMmBvx+jgysKmoBp0fA==":"mbr-8.jpg","Ben0qzMt35QbHdwtB8kV+w==":"dji-725.jpg","mjL/FJQv3h/uhi1MAybJ6w==":"dji-729.jpg","IENEwC2iT8ggklWji9DWmg==":"dsc-22.jpg","TPnik9Q01FJx9UZKvrULFQ==":"dsc-19.jpg","esrz2hZL4KakpujRe7l6RA==":"dsc-16.jpg","8BXieqI/wa2HauG+Gw9gTg==":"fb-img-1556927459522.jpg","jy+nCTQYXCIZrBPEIvomIw==":"dji-731.jpg","kRjyC/kWHwNvkihp8lS4CQ==":"dji-747.jpg","+4y6jQaq49yVeTIc4uDBzA==":"dji-778.jpg","FsHH0PGQz42uQ01c5qS88g==":"dji-768.jpg","kpUzIkdiAGly36CxgpkoSQ==":"dji-819.jpg","+rU+fugEW7IB4s7+paB6Vw==":"dji-801.jpg","UAc7kepzJPkrSn4uqTRvmw==":"background4.jpg","KF+UvQTaZhFzc9uFnxCGfQ==":"dsc-22-2000x1325.jpg","QZABagWAIi8tYagWmYnQXQ==":"dsc-19-2000x1325.jpg","V1YIgv24UdKVKpscVwDWAQ==":"kujicam-2019-05-04-00-48-11-developed-1-890x501.jpg","ZPSpbQT6lT67r8lJlsQH2w==":"kujicam-2019-05-04-00-48-11-developed-1-1466x825.jpg","VRp64oxxWLGnbkDxF+U9sw==":"kujicam-2019-05-04-00-48-11-developed-1-742x417.jpg","rWC4Ht5lzXi9TCS7YuU9jw==":"kujicam-2019-05-04-00-48-11-developed-1-676x380.jpg","kLuqNFs9bxON1MSdriilcQ==":"mbr-676x456.jpg","iCWakbkxA7w6MD4wEtp0aw==":"mbr-676x451.jpg","4lSL+CyD/RTeNixZzZxQ1Q==":"mbr-1-676x451.jpg","S6lkBAqRpdOHbOkMB13BKg==":"mbr-1-676x456.jpg","xMLEYPql+YyLp3df4sQ+4Q==":"mbr-2-676x451.jpg","pa5Dkwo/T1qgW/t0h+fQvA==":"background5.jpg","awZJVV+W4r/utMvbyZAnhw==":"kujicam-2019-05-04-00-48-11-developed-2-676x380.jpg","QOKIUhxjB1Er5/DdkuxqCw==":"mbr-2-676x456.jpg","+e8b+1o5GXsDBTg3uK1afg==":"mbr-3-676x451.jpg","c/wDobBB7NmJ8PLm220pHA==":"1_bmqsica_dpkrtsarwnvnoq-960x120.png","7m+3OCjbZH3BT1naLsmUiA==":"screen%20shot%202019-05-05%20at%2012.21.56%20am-1602x1028.png","RwoxTkrRrzirqntEfmw95Q==":"1_ntpn8oep3uepvzdpb8uimq-1600x575.jpg","pzdtv0R7Jp8havSsolwZag==":"screen%20shot%202019-05-05%20at%2012.21.56%20am-1398x897.png","SZGzPNQmMsiYTPqtWW8flw==":"screen%20shot%202019-05-05%20at%206.25.09%20pm-1672x1156.png","X/PINPQFhgiqcPKvMsChUw==":"1__162hyygho-zyncprh2gnq-960x120.png","ljXh2Uq/a+SD2sVlWBHNHA==":"screen%20shot%202019-05-05%20at%206.30.29%20pm-974x622.png","2fVTJA3eGfDWsCCfP525BA==":"dji-725-2000x1500.jpg","ckxZ+91LxRID4a8fbM+Jxg==":"dji-731-2000x1500.jpg","xFkQvqzDUskq2xvsNMd6SQ==":"dji-729-2000x1500.jpg","Tz4w9wCumAdS/4nMqTqsgg==":"dji-778-2000x1500.jpg","MwUSwmJey5heiwSuhPdIWA==":"dji-768-2000x1500.jpg","/5TxP6rB5Xsj6wML99MSww==":"logo2.png","+KYgW+i6D/avvNMcqjPLVQ==":"koinobori-192x192.png","ttKruYsRhZ19RD7nMqWW2A==":"26330428_1511974088915368_7717623298208563200_n-1080x893.jpg","sBsPkNWpxCCZON4HKw8jnw==":"26330428_1511974088915368_7717623298208563200_n-1-1080x893.jpg","/Yp2JD5nxmjF2rYxNktpjw==":"26330428_1511974088915368_7717623298208563200_n-676x559.jpg","9J46aVpX18SCV2z8zrVcTg==":"1970-01-01%2003.00.00%2016-1554x2072.jpg","zsnX6A2zs/axwj68JPQ5GQ==":"1970-01-01%2003.00.00%2013-1554x1166.jpg","JeUv6gkmN8nZak3PTU2J9A==":"img_20190410-184352-902x677.jpg","ZDgfm9olkwAzz3mdWW3IYg==":"img_20190410-184352-522x392.jpg","Ba8fJXg/Flb2R89oIOUevQ==":"1970-01-01%2003.00.00%2016-522x696.jpg","N2vgiglvM8j/GUxv/QDfpA==":"img_20190410-184352-902x1203.jpg","cDy6SxkvOm+j5QusqkaN4Q==":"mbr-1302x732.jpg","Qj7tXfHWStTGhHwIe0D20Q==":"screen%20shot%202019-05-05%20at%2011.52.38%20pm-1302x732.png","gcO/iFca+527Znw4zX5HUg==":"57109867_2342467282482904_682967883885576192_o-2000x1324.jpg","xyD4qgowMEiwDtAx6tWCRA==":"dji-801-2000x1500.jpg","pfVFL9IeAjD7vSNyq3sn0A==":"dji-793-2000x1500.jpg"}